_sm3.cpython-39-darwin.so
sm3utils-0.1.5.dist-info/RECORD
sm3utils-0.1.5.dist-info/LICENSE
sm3utils-0.1.5.dist-info/WHEEL
sm3utils-0.1.5.dist-info/top_level.txt
sm3utils-0.1.5.dist-info/METADATA
sm3utils/sm3.c
sm3utils/bind.c
sm3utils/__init__.py
sm3utils/core.py
sm3utils/sm3.h
