Metadata-Version: 2.4
Name: sm3utils
Version: 0.1.5
Summary: SM3 Cryptographic Hash Algorithm.
Author: rRR0VrFP
Maintainer: rRR0VrFP
License: Apache License, Version 2.0
Keywords: sm3
Classifier: Development Status :: 5 - Production/Stable
Classifier: Intended Audience :: Developers
Classifier: Topic :: Software Development :: Libraries :: Python Modules
Classifier: License :: OSI Approved :: Apache Software License
Classifier: Programming Language :: Python :: 3
Classifier: Programming Language :: Python :: 3 :: Only
License-File: LICENSE
Dynamic: author
Dynamic: classifier
Dynamic: description
Dynamic: description-content-type
Dynamic: keywords
Dynamic: license
Dynamic: license-file
Dynamic: maintainer
Dynamic: summary
